kubens/__init__.py
kubens/kubens.py
kubens-1.2.5.dist-info/LICENSE
kubens-1.2.5.dist-info/METADATA
kubens-1.2.5.dist-info/WHEEL
kubens-1.2.5.dist-info/entry_points.txt
kubens-1.2.5.dist-info/top_level.txt
kubens-1.2.5.dist-info/RECORD
