Metadata-Version: 2.1
Name: kubens
Version: 1.2.5
Summary: Terminal kubectl namespace selector
Home-page: https://github.com/roubles/kubens
Download-URL: https://github.com/roubles/kubens/tarball/1.2.5
Author: roubles
Author-email: rouble@gmail.com
License: MIT
License-File: LICENSE
Requires-Dist: pick==2.3.2
